pixi.py
pixi_cli-0.2.1.dist-info/LICENSE
pixi_cli-0.2.1.dist-info/METADATA
pixi_cli-0.2.1.dist-info/WHEEL
pixi_cli-0.2.1.dist-info/entry_points.txt
pixi_cli-0.2.1.dist-info/top_level.txt
pixi_cli-0.2.1.dist-info/RECORD
