Metadata-Version: 2.1
Name: pixi-cli
Version: 0.2.1
Summary: A command-line tool for basic image processing tasks.
Home-page: https://github.com/zainkarim/pixi-cli
Author: Zain Karim
Author-email: zain@zainkarim.com
Classifier: Programming Language :: Python :: 3
Classifier: License :: OSI Approved :: MIT License
Classifier: Operating System :: OS Independent
Requires-Python: >=3.6
License-File: LICENSE
Requires-Dist: Pillow
Requires-Dist: cairosvg
